{
  "schemaVersion": 1,
  "id": "enchantips",
  "version": "${version}",

  "name": "Enchantips",
  "description": "Provides utilities for viewing things related to enchantments.",
  "authors": [
    "FEDPOL1"
  ],
  "contact": {
    "sources": "https://github.com/fedpol1/enchantips",
    "issues": "https://github.com/fedpol1/enchantips/issues"
  },

  "license": "ARR",
  "icon": "assets/enchantips/icon.png",

  "environment": "*",
  "entrypoints": {
    "main": [],
    "client": [ "com.fedpol1.enchantips.EnchantipsClient" ],
    "modmenu": [ "com.fedpol1.enchantips.ModMenuEntry" ]
  },
  "mixins": [
    "enchantips.mixins.json"
  ],

  "depends": {
    "fabricloader": ">=0.15.11",
    "fabric-api": ">=0.100.0+1.21",
    "minecraft": ">=1.21.2",
    "java": ">=21"
  },
  "suggests": {
    "modmenu": ">=12.0.0",
    "yet-another-config-lib": ">=3.6.1"
  }
}
